{
  "color": {
    "primary": {
      "100": {
        "value": "202, 240, 248",
        "filePath": "src/tokens/colors/base.json",
        "isSource": true,
        "original": {
          "value": "202, 240, 248"
        },
        "name": "color-primary-100",
        "attributes": {
          "category": "color",
          "type": "primary",
          "item": "100"
        },
        "path": [
          "color",
          "primary",
          "100"
        ]
      },
      "200": {
        "value": "173, 232, 244",
        "filePath": "src/tokens/colors/base.json",
        "isSource": true,
        "original": {
          "value": "173, 232, 244"
        },
        "name": "color-primary-200",
        "attributes": {
          "category": "color",
          "type": "primary",
          "item": "200"
        },
        "path": [
          "color",
          "primary",
          "200"
        ]
      },
      "300": {
        "value": "144, 224, 239",
        "filePath": "src/tokens/colors/base.json",
        "isSource": true,
        "original": {
          "value": "144, 224, 239"
        },
        "name": "color-primary-300",
        "attributes": {
          "category": "color",
          "type": "primary",
          "item": "300"
        },
        "path": [
          "color",
          "primary",
          "300"
        ]
      },
      "400": {
        "value": "72, 202, 228",
        "filePath": "src/tokens/colors/base.json",
        "isSource": true,
        "original": {
          "value": "72, 202, 228"
        },
        "name": "color-primary-400",
        "attributes": {
          "category": "color",
          "type": "primary",
          "item": "400"
        },
        "path": [
          "color",
          "primary",
          "400"
        ]
      },
      "500": {
        "value": "0, 180, 216",
        "comment": "main hue",
        "filePath": "src/tokens/colors/base.json",
        "isSource": true,
        "original": {
          "value": "0, 180, 216",
          "comment": "main hue"
        },
        "name": "color-primary-500",
        "attributes": {
          "category": "color",
          "type": "primary",
          "item": "500"
        },
        "path": [
          "color",
          "primary",
          "500"
        ]
      },
      "600": {
        "value": "0, 150, 199",
        "filePath": "src/tokens/colors/base.json",
        "isSource": true,
        "original": {
          "value": "0, 150, 199"
        },
        "name": "color-primary-600",
        "attributes": {
          "category": "color",
          "type": "primary",
          "item": "600"
        },
        "path": [
          "color",
          "primary",
          "600"
        ]
      },
      "700": {
        "value": "0, 119, 182",
        "filePath": "src/tokens/colors/base.json",
        "isSource": true,
        "original": {
          "value": "0, 119, 182"
        },
        "name": "color-primary-700",
        "attributes": {
          "category": "color",
          "type": "primary",
          "item": "700"
        },
        "path": [
          "color",
          "primary",
          "700"
        ]
      },
      "800": {
        "value": "2, 62, 138",
        "filePath": "src/tokens/colors/base.json",
        "isSource": true,
        "original": {
          "value": "2, 62, 138"
        },
        "name": "color-primary-800",
        "attributes": {
          "category": "color",
          "type": "primary",
          "item": "800"
        },
        "path": [
          "color",
          "primary",
          "800"
        ]
      },
      "900": {
        "value": "3, 4, 94",
        "filePath": "src/tokens/colors/base.json",
        "isSource": true,
        "original": {
          "value": "3, 4, 94"
        },
        "name": "color-primary-900",
        "attributes": {
          "category": "color",
          "type": "primary",
          "item": "900"
        },
        "path": [
          "color",
          "primary",
          "900"
        ]
      }
    },
    "accent": {
      "100": {
        "value": "153, 226, 180",
        "filePath": "src/tokens/colors/base.json",
        "isSource": true,
        "original": {
          "value": "153, 226, 180"
        },
        "name": "color-accent-100",
        "attributes": {
          "category": "color",
          "type": "accent",
          "item": "100"
        },
        "path": [
          "color",
          "accent",
          "100"
        ]
      },
      "200": {
        "value": "136, 212, 171",
        "filePath": "src/tokens/colors/base.json",
        "isSource": true,
        "original": {
          "value": "136, 212, 171"
        },
        "name": "color-accent-200",
        "attributes": {
          "category": "color",
          "type": "accent",
          "item": "200"
        },
        "path": [
          "color",
          "accent",
          "200"
        ]
      },
      "300": {
        "value": "120, 198, 163",
        "filePath": "src/tokens/colors/base.json",
        "isSource": true,
        "original": {
          "value": "120, 198, 163"
        },
        "name": "color-accent-300",
        "attributes": {
          "category": "color",
          "type": "accent",
          "item": "300"
        },
        "path": [
          "color",
          "accent",
          "300"
        ]
      },
      "400": {
        "value": "103, 185, 154",
        "filePath": "src/tokens/colors/base.json",
        "isSource": true,
        "original": {
          "value": "103, 185, 154"
        },
        "name": "color-accent-400",
        "attributes": {
          "category": "color",
          "type": "accent",
          "item": "400"
        },
        "path": [
          "color",
          "accent",
          "400"
        ]
      },
      "500": {
        "value": "86, 171, 145",
        "filePath": "src/tokens/colors/base.json",
        "isSource": true,
        "original": {
          "value": "86, 171, 145"
        },
        "name": "color-accent-500",
        "attributes": {
          "category": "color",
          "type": "accent",
          "item": "500"
        },
        "path": [
          "color",
          "accent",
          "500"
        ]
      },
      "600": {
        "value": "70, 157, 137",
        "filePath": "src/tokens/colors/base.json",
        "isSource": true,
        "original": {
          "value": "70, 157, 137"
        },
        "name": "color-accent-600",
        "attributes": {
          "category": "color",
          "type": "accent",
          "item": "600"
        },
        "path": [
          "color",
          "accent",
          "600"
        ]
      },
      "700": {
        "value": "53, 143, 128",
        "filePath": "src/tokens/colors/base.json",
        "isSource": true,
        "original": {
          "value": "53, 143, 128"
        },
        "name": "color-accent-700",
        "attributes": {
          "category": "color",
          "type": "accent",
          "item": "700"
        },
        "path": [
          "color",
          "accent",
          "700"
        ]
      },
      "800": {
        "value": "36, 130, 119",
        "filePath": "src/tokens/colors/base.json",
        "isSource": true,
        "original": {
          "value": "36, 130, 119"
        },
        "name": "color-accent-800",
        "attributes": {
          "category": "color",
          "type": "accent",
          "item": "800"
        },
        "path": [
          "color",
          "accent",
          "800"
        ]
      },
      "900": {
        "value": "20, 116, 111",
        "filePath": "src/tokens/colors/base.json",
        "isSource": true,
        "original": {
          "value": "20, 116, 111"
        },
        "name": "color-accent-900",
        "attributes": {
          "category": "color",
          "type": "accent",
          "item": "900"
        },
        "path": [
          "color",
          "accent",
          "900"
        ]
      }
    },
    "warning": {
      "100": {
        "value": "255, 170, 0",
        "filePath": "src/tokens/colors/base.json",
        "isSource": true,
        "original": {
          "value": "255, 170, 0"
        },
        "name": "color-warning-100",
        "attributes": {
          "category": "color",
          "type": "warning",
          "item": "100"
        },
        "path": [
          "color",
          "warning",
          "100"
        ]
      },
      "200": {
        "value": "255, 158, 0",
        "filePath": "src/tokens/colors/base.json",
        "isSource": true,
        "original": {
          "value": "255, 158, 0"
        },
        "name": "color-warning-200",
        "attributes": {
          "category": "color",
          "type": "warning",
          "item": "200"
        },
        "path": [
          "color",
          "warning",
          "200"
        ]
      },
      "300": {
        "value": "255, 145, 0",
        "filePath": "src/tokens/colors/base.json",
        "isSource": true,
        "original": {
          "value": "255, 145, 0"
        },
        "name": "color-warning-300",
        "attributes": {
          "category": "color",
          "type": "warning",
          "item": "300"
        },
        "path": [
          "color",
          "warning",
          "300"
        ]
      },
      "400": {
        "value": "255, 133, 0",
        "filePath": "src/tokens/colors/base.json",
        "isSource": true,
        "original": {
          "value": "255, 133, 0"
        },
        "name": "color-warning-400",
        "attributes": {
          "category": "color",
          "type": "warning",
          "item": "400"
        },
        "path": [
          "color",
          "warning",
          "400"
        ]
      },
      "500": {
        "value": "255, 121, 0",
        "filePath": "src/tokens/colors/base.json",
        "isSource": true,
        "original": {
          "value": "255, 121, 0"
        },
        "name": "color-warning-500",
        "attributes": {
          "category": "color",
          "type": "warning",
          "item": "500"
        },
        "path": [
          "color",
          "warning",
          "500"
        ]
      },
      "600": {
        "value": "255, 109, 0",
        "filePath": "src/tokens/colors/base.json",
        "isSource": true,
        "original": {
          "value": "255, 109, 0"
        },
        "name": "color-warning-600",
        "attributes": {
          "category": "color",
          "type": "warning",
          "item": "600"
        },
        "path": [
          "color",
          "warning",
          "600"
        ]
      },
      "700": {
        "value": "255, 96, 0",
        "filePath": "src/tokens/colors/base.json",
        "isSource": true,
        "original": {
          "value": "255, 96, 0"
        },
        "name": "color-warning-700",
        "attributes": {
          "category": "color",
          "type": "warning",
          "item": "700"
        },
        "path": [
          "color",
          "warning",
          "700"
        ]
      },
      "800": {
        "value": "255, 84, 0",
        "filePath": "src/tokens/colors/base.json",
        "isSource": true,
        "original": {
          "value": "255, 84, 0"
        },
        "name": "color-warning-800",
        "attributes": {
          "category": "color",
          "type": "warning",
          "item": "800"
        },
        "path": [
          "color",
          "warning",
          "800"
        ]
      },
      "900": {
        "value": "255, 72, 0",
        "filePath": "src/tokens/colors/base.json",
        "isSource": true,
        "original": {
          "value": "255, 72, 0"
        },
        "name": "color-warning-900",
        "attributes": {
          "category": "color",
          "type": "warning",
          "item": "900"
        },
        "path": [
          "color",
          "warning",
          "900"
        ]
      }
    },
    "gray": {
      "100": {
        "value": "248, 248, 248",
        "filePath": "src/tokens/colors/base.json",
        "isSource": true,
        "original": {
          "value": "248, 248, 248"
        },
        "name": "color-gray-100",
        "attributes": {
          "category": "color",
          "type": "gray",
          "item": "100"
        },
        "path": [
          "color",
          "gray",
          "100"
        ]
      },
      "200": {
        "value": "220, 220, 220",
        "filePath": "src/tokens/colors/base.json",
        "isSource": true,
        "original": {
          "value": "220, 220, 220"
        },
        "name": "color-gray-200",
        "attributes": {
          "category": "color",
          "type": "gray",
          "item": "200"
        },
        "path": [
          "color",
          "gray",
          "200"
        ]
      },
      "300": {
        "value": "190, 190, 190",
        "filePath": "src/tokens/colors/base.json",
        "isSource": true,
        "original": {
          "value": "190, 190, 190"
        },
        "name": "color-gray-300",
        "attributes": {
          "category": "color",
          "type": "gray",
          "item": "300"
        },
        "path": [
          "color",
          "gray",
          "300"
        ]
      },
      "400": {
        "value": "170, 170, 170",
        "filePath": "src/tokens/colors/base.json",
        "isSource": true,
        "original": {
          "value": "170, 170, 170"
        },
        "name": "color-gray-400",
        "attributes": {
          "category": "color",
          "type": "gray",
          "item": "400"
        },
        "path": [
          "color",
          "gray",
          "400"
        ]
      },
      "500": {
        "value": "150, 150, 150",
        "filePath": "src/tokens/colors/base.json",
        "isSource": true,
        "original": {
          "value": "150, 150, 150"
        },
        "name": "color-gray-500",
        "attributes": {
          "category": "color",
          "type": "gray",
          "item": "500"
        },
        "path": [
          "color",
          "gray",
          "500"
        ]
      },
      "600": {
        "value": "130, 130, 130",
        "filePath": "src/tokens/colors/base.json",
        "isSource": true,
        "original": {
          "value": "130, 130, 130"
        },
        "name": "color-gray-600",
        "attributes": {
          "category": "color",
          "type": "gray",
          "item": "600"
        },
        "path": [
          "color",
          "gray",
          "600"
        ]
      },
      "700": {
        "value": "110, 110, 110",
        "filePath": "src/tokens/colors/base.json",
        "isSource": true,
        "original": {
          "value": "110, 110, 110"
        },
        "name": "color-gray-700",
        "attributes": {
          "category": "color",
          "type": "gray",
          "item": "700"
        },
        "path": [
          "color",
          "gray",
          "700"
        ]
      },
      "800": {
        "value": "90, 90, 90",
        "filePath": "src/tokens/colors/base.json",
        "isSource": true,
        "original": {
          "value": "90, 90, 90"
        },
        "name": "color-gray-800",
        "attributes": {
          "category": "color",
          "type": "gray",
          "item": "800"
        },
        "path": [
          "color",
          "gray",
          "800"
        ]
      },
      "900": {
        "value": "70, 70, 70",
        "filePath": "src/tokens/colors/base.json",
        "isSource": true,
        "original": {
          "value": "70, 70, 70"
        },
        "name": "color-gray-900",
        "attributes": {
          "category": "color",
          "type": "gray",
          "item": "900"
        },
        "path": [
          "color",
          "gray",
          "900"
        ]
      }
    }
  },
  "spacing": {
    "0": {
      "value": "0px",
      "filePath": "src/tokens/spacing/base.json",
      "isSource": true,
      "original": {
        "value": "0px"
      },
      "name": "spacing-0",
      "attributes": {
        "category": "spacing",
        "type": "0"
      },
      "path": [
        "spacing",
        "0"
      ]
    },
    "1": {
      "value": "0.5em",
      "filePath": "src/tokens/spacing/base.json",
      "isSource": true,
      "original": {
        "value": "0.5em"
      },
      "name": "spacing-1",
      "attributes": {
        "category": "spacing",
        "type": "1"
      },
      "path": [
        "spacing",
        "1"
      ]
    },
    "2": {
      "value": "1rem",
      "filePath": "src/tokens/spacing/base.json",
      "isSource": true,
      "original": {
        "value": "1rem"
      },
      "name": "spacing-2",
      "attributes": {
        "category": "spacing",
        "type": "2"
      },
      "path": [
        "spacing",
        "2"
      ]
    },
    "3": {
      "value": "1.5rem",
      "filePath": "src/tokens/spacing/base.json",
      "isSource": true,
      "original": {
        "value": "1.5rem"
      },
      "name": "spacing-3",
      "attributes": {
        "category": "spacing",
        "type": "3"
      },
      "path": [
        "spacing",
        "3"
      ]
    },
    "4": {
      "value": "2rem",
      "filePath": "src/tokens/spacing/base.json",
      "isSource": true,
      "original": {
        "value": "2rem"
      },
      "name": "spacing-4",
      "attributes": {
        "category": "spacing",
        "type": "4"
      },
      "path": [
        "spacing",
        "4"
      ]
    },
    "6": {
      "value": "3rem",
      "filePath": "src/tokens/spacing/base.json",
      "isSource": true,
      "original": {
        "value": "3rem"
      },
      "name": "spacing-6",
      "attributes": {
        "category": "spacing",
        "type": "6"
      },
      "path": [
        "spacing",
        "6"
      ]
    },
    "8": {
      "value": "4rem",
      "filePath": "src/tokens/spacing/base.json",
      "isSource": true,
      "original": {
        "value": "4rem"
      },
      "name": "spacing-8",
      "attributes": {
        "category": "spacing",
        "type": "8"
      },
      "path": [
        "spacing",
        "8"
      ]
    },
    "12": {
      "value": "6em",
      "filePath": "src/tokens/spacing/base.json",
      "isSource": true,
      "original": {
        "value": "6em"
      },
      "name": "spacing-12",
      "attributes": {
        "category": "spacing",
        "type": "12"
      },
      "path": [
        "spacing",
        "12"
      ]
    },
    "16": {
      "value": "8rem",
      "filePath": "src/tokens/spacing/base.json",
      "isSource": true,
      "original": {
        "value": "8rem"
      },
      "name": "spacing-16",
      "attributes": {
        "category": "spacing",
        "type": "16"
      },
      "path": [
        "spacing",
        "16"
      ]
    },
    "20": {
      "value": "10rem",
      "filePath": "src/tokens/spacing/base.json",
      "isSource": true,
      "original": {
        "value": "10rem"
      },
      "name": "spacing-20",
      "attributes": {
        "category": "spacing",
        "type": "20"
      },
      "path": [
        "spacing",
        "20"
      ]
    },
    "30": {
      "value": "15rem",
      "filePath": "src/tokens/spacing/base.json",
      "isSource": true,
      "original": {
        "value": "15rem"
      },
      "name": "spacing-30",
      "attributes": {
        "category": "spacing",
        "type": "30"
      },
      "path": [
        "spacing",
        "30"
      ]
    },
    "40": {
      "value": "20rem",
      "filePath": "src/tokens/spacing/base.json",
      "isSource": true,
      "original": {
        "value": "20rem"
      },
      "name": "spacing-40",
      "attributes": {
        "category": "spacing",
        "type": "40"
      },
      "path": [
        "spacing",
        "40"
      ]
    }
  }
}